sidewalkify/__init__.py
sidewalkify/__main__.py
sidewalkify/draw/__init__.py
sidewalkify/draw/draw.py
sidewalkify/draw/trim.py
sidewalkify/draw/utils.py
sidewalkify/graph/__init__.py
sidewalkify/graph/graph.py
sidewalkify/graph/utils.py
sidewalkify-0.2.1.dist-info/DESCRIPTION.rst
sidewalkify-0.2.1.dist-info/METADATA
sidewalkify-0.2.1.dist-info/RECORD
sidewalkify-0.2.1.dist-info/WHEEL
sidewalkify-0.2.1.dist-info/entry_points.txt
sidewalkify-0.2.1.dist-info/metadata.json
sidewalkify-0.2.1.dist-info/top_level.txt
