Metadata-Version: 2.0
Name: sidewalkify
Version: 0.2.1
Summary: `sidewalkify` is a Python library and command line application for drawing sidewalk lines from street centerline data.
Home-page: https://github.com/accessmap/sidewalkify
Author: UNKNOWN
Author-email: UNKNOWN
License: MIT / Apache 2.0
Download-URL: https://github.com/accessmap/sidewalkify.git
Platform: UNKNOWN
Classifier: Programming Language :: Python
Classifier: Programming Language :: Python :: 3.5
Classifier: Programming Language :: Python :: 3 :: Only
Requires-Dist: Shapely
Requires-Dist: click
Requires-Dist: geopandas
Requires-Dist: networkx
Requires-Dist: numpy
